iploc/__init__.py
iploc/api.py
iploc-0.2.0.dist-info/METADATA
iploc-0.2.0.dist-info/WHEEL
iploc-0.2.0.dist-info/top_level.txt
iploc-0.2.0.dist-info/RECORD
