Metadata-Version: 2.4
Name: iploc
Version: 0.2.0
Summary: Python client for IP lookup
Author: ip-loc-dev
License: MIT
Classifier: Programming Language :: Python :: 3
Classifier: License :: OSI Approved :: MIT License
Classifier: Operating System :: OS Independent
Requires-Python: >=3.8
Requires-Dist: requests>=2.30.0
Dynamic: author
Dynamic: classifier
Dynamic: description-content-type
Dynamic: license
Dynamic: requires-dist
Dynamic: requires-python
Dynamic: summary
